tf/ctc/__init__.py
tf/ctc/__init__.pyi
tf/ctc/decoding.py
tf/ctc/logits.py
tf/ctc/loss_.py
tf/ctc/metrics.py
tf/ctc/test.py
tf/ctc/tests/test_decoding.py
tf/ctc/tests/test_loss.py
tf/ctc/tests/test_metrics.py
tf_ctc-0.1.8.dist-info/METADATA
tf_ctc-0.1.8.dist-info/WHEEL
tf_ctc-0.1.8.dist-info/top_level.txt
tf_ctc-0.1.8.dist-info/RECORD
