Metadata-Version: 2.1
Name: tf-ctc
Version: 0.1.8
Summary: CTC with tensorflow, simplified
Author-email: Marcel Claramunt <marcel@moveread.com>
Project-URL: repo, https://github.com/marciclabas/tensorflow-ocr
Requires-Python: >=3.10
Requires-Dist: jaxtyping
Requires-Dist: tf-tools
Requires-Dist: tensorflow
Requires-Dist: lazy-loader
Provides-Extra: test
Requires-Dist: pytest ; extra == 'test'
Requires-Dist: hypothesis ; extra == 'test'
